big_sky_yag/__init__.py
big_sky_yag/attributes.py
big_sky_yag/bit_handling.py
big_sky_yag/device.py
big_sky_yag/interlock.py
big_sky_yag/py.typed
big_sky_yag-0.1.0.dist-info/LICENSE
big_sky_yag-0.1.0.dist-info/WHEEL
big_sky_yag-0.1.0.dist-info/METADATA
big_sky_yag-0.1.0.dist-info/RECORD
