Metadata-Version: 2.1
Name: big-sky-yag
Version: 0.1.0
Summary: 
Home-page: https://github.com/ograsdijk/Big-Sky-YAG
Author: ograsdijk
Author-email: o.grasdijk@gmail.com
Requires-Python: >=3.8,<4.0
Classifier: Programming Language :: Python :: 3
Classifier: Programming Language :: Python :: 3.8
Classifier: Programming Language :: Python :: 3.9
Classifier: Programming Language :: Python :: 3.10
Classifier: Programming Language :: Python :: 3.11
Requires-Dist: PyVISA (>=1.12.0,<2.0.0)
Project-URL: Repository, https://github.com/ograsdijk/Big-Sky-YAG
